{
  "Object": "Classes",
  "Data": [
    {
      "Name": "Morning Yoga",
      "Date": "2025-01-10",
      "Time": "09:00",
      "Minimum_Membership_Access": "Basic",
      "Trainer": "T001",
      "Members": [
        "olivia.green@gymfit.com",
        "noah.anderson@gymfit.com",
        "william.moore@gymfit.com",
        "isabella.young@gymfit.com",
        "mia.wright@gymfit.com",
        "henry.adams@gymfit.com",
        "michael.rivera@gymfit.com",
        "evelyn.gray@gymfit.com",
        "abigail.foster@gymfit.com",
        "matthew.cox@gymfit.com"
      ]
    },
    {
      "Name": "Spin Class",
      "Date": "2025-01-10",
      "Time": "10:30",
      "Minimum_Membership_Access": "Premium",
      "Trainer": "T002",
      "Members": [
        "liam.carter@gymfit.com",
        "ava.miller@gymfit.com",
        "sophia.clark@gymfit.com",
        "benjamin.king@gymfit.com",
        "lucas.scott@gymfit.com",
        "amelia.perez@gymfit.com",
        "harper.stewart@gymfit.com",
        "daniel.hughes@gymfit.com",
        "jacob.ross@gymfit.com",
        "elizabeth.howard@gymfit.com"
      ]
    },
    {
      "Name": "Pilates",
      "Date": "2025-01-11",
      "Time": "09:30",
      "Minimum_Membership_Access": "Basic",
      "Trainer": "T003",
      "Members": [
        "olivia.green@gymfit.com",
        "emma.thompson@gymfit.com",
        "william.moore@gymfit.com",
        "james.hall@gymfit.com",
        "mia.wright@gymfit.com",
        "charlotte.baker@gymfit.com",
        "michael.rivera@gymfit.com",
        "ethan.torres@gymfit.com",
        "abigail.foster@gymfit.com",
        "emily.ward@gymfit.com"
      ]
    },
    {
      "Name": "HIIT",
      "Date": "2025-01-11",
      "Time": "18:00",
      "Minimum_Membership_Access": "Premium",
      "Trainer": "T004",
      "Members": [
        "liam.carter@gymfit.com",
        "noah.anderson@gymfit.com",
        "sophia.clark@gymfit.com",
        "isabella.young@gymfit.com",
        "lucas.scott@gymfit.com",
        "henry.adams@gymfit.com",
        "harper.stewart@gymfit.com",
        "evelyn.gray@gymfit.com",
        "jacob.ross@gymfit.com",
        "matthew.cox@gymfit.com"
      ]
    },
    {
      "Name": "Zumba",
      "Date": "2025-01-12",
      "Time": "17:30",
      "Minimum_Membership_Access": "Basic",
      "Trainer": "T005",
      "Members": [
        "emma.thompson@gymfit.com",
        "ava.miller@gymfit.com",
        "james.hall@gymfit.com",
        "benjamin.king@gymfit.com",
        "charlotte.baker@gymfit.com",
        "amelia.perez@gymfit.com",
        "ethan.torres@gymfit.com",
        "daniel.hughes@gymfit.com",
        "emily.ward@gymfit.com",
        "elizabeth.howard@gymfit.com"
      ]
    }
  ]
}
